core_evals/scicode/__init__.py
core_evals/scicode/framework.yml
core_evals/scicode/framework_entrypoint.py
core_evals/scicode/output.py
nvidia_scicode-25.11.dist-info/licenses/LICENSE
scicode/__init__.py
scicode/__main__.py
scicode/compare/__init__.py
scicode/compare/cmp.py
scicode/data/13.6.txt
scicode/data/62.1.txt
scicode/data/76.3.txt
scicode/data/__init__.py
scicode/data/background_comment_template.txt
scicode/data/downloader.py
scicode/data/multistep_template.txt
scicode/data/problems_all.jsonl
scicode/data/problems_dev.jsonl
scicode/gen/__init__.py
scicode/gen/gencode_json.py
scicode/gen/models.py
scicode/parse/__init__.py
scicode/parse/parse.py
scicode/utils/__init__.py
scicode/utils/log.py
nvidia_scicode-25.11.dist-info/METADATA
nvidia_scicode-25.11.dist-info/WHEEL
nvidia_scicode-25.11.dist-info/entry_points.txt
nvidia_scicode-25.11.dist-info/top_level.txt
nvidia_scicode-25.11.dist-info/RECORD
