Metadata-Version: 2.4
Name: nvidia-scicode
Version: 25.11
Summary: SciCode - packaged by NVIDIA
Author: NVIDIA, SciCode
License:                                  Apache License
Project-URL: Original Project, https://github.com/scicode-bench/SciCode
Project-URL: Paper, https://arxiv.org/abs/2407.13168
Project-URL: Homepage, https://scicode-bench.github.io/
Keywords: nlp,code
Classifier: Development Status :: 5 - Production/Stable
Classifier: Programming Language :: Python :: 3
Classifier: License :: OSI Approved :: Apache Software License
Classifier: Operating System :: OS Independent
Requires-Python: >=3.10
License-File: LICENSE
Requires-Dist: h5py
Requires-Dist: tqdm
Requires-Dist: openai
Requires-Dist: google-generativeai
Requires-Dist: anthropic
Requires-Dist: config
Requires-Dist: rich
Requires-Dist: pytest
Requires-Dist: pytest-cov
Requires-Dist: litellm
Requires-Dist: numpy
Requires-Dist: scipy
Requires-Dist: matplotlib
Requires-Dist: sympy
Requires-Dist: omegaconf
Requires-Dist: nemo-evaluator
Dynamic: license-file
